__init__.py
_version.py
captcha.py
ecourt.py
storage.py
cli/__init__.py
entities/__init__.py
entities/act_type.py
entities/case.py
entities/case_type.py
entities/cause_list.py
entities/court.py
entities/fir.py
entities/hearing.py
entities/objection.py
entities/order.py
entities/party.py
parsers/__init__.py
parsers/case_details.py
parsers/cases.py
parsers/cause_lists.py
parsers/hearing_details.py
parsers/options.py
parsers/orders.py
parsers/utils.py
ecourts-0.0.8.dist-info/LICENSE
ecourts-0.0.8.dist-info/METADATA
ecourts-0.0.8.dist-info/WHEEL
ecourts-0.0.8.dist-info/entry_points.txt
ecourts-0.0.8.dist-info/top_level.txt
ecourts-0.0.8.dist-info/RECORD
