Metadata-Version: 2.1
Name: ecourts
Version: 0.0.8
Summary: ecourts is a information retrieval tool for Indian High Courts.
Author: Abhay Rana
Keywords: ecourts,legal-research,india,judiciary,law,information-retrieval
Requires-Python: >=3.9
License-File: LICENSE
Requires-Dist: requests~=2.32
Requires-Dist: beautifulsoup4~=4.12
Requires-Dist: opencv-python~=4.10.0
Requires-Dist: click~=8.1
Requires-Dist: tabulate~=0.9
Requires-Dist: tqdm~=4.67
Provides-Extra: docs
Requires-Dist: pdoc3~=0.11; extra == "docs"
Provides-Extra: test
Requires-Dist: pytest~=8.3; extra == "test"
Requires-Dist: pytest-cov<7,>=5; extra == "test"
Requires-Dist: PyYAML~=6.0; extra == "test"
Requires-Dist: pytest-recording~=0.13; extra == "test"
Requires-Dist: wat-inspector~=0.3; extra == "test"
